classicle/__init__.py
classicle/frozen_instance.py
classicle-0.1.0.dist-info/METADATA
classicle-0.1.0.dist-info/WHEEL
classicle-0.1.0.dist-info/licenses/LICENSE
classicle-0.1.0.dist-info/RECORD
