Metadata-Version: 2.4
Name: classicle
Version: 0.1.0
Summary: Immutable constant namespaces with dataclass-like ergonomics
Author: zkurtz
License: MIT
License-File: LICENSE
Requires-Python: >=3.11
